matroid/__init__.py
matroid/client.py
matroid/error.py
matroid/version.py
matroid/src/__init__.py
matroid/src/accounts.py
matroid/src/collections.py
matroid/src/detectors.py
matroid/src/helpers.py
matroid/src/images.py
matroid/src/labels.py
matroid/src/sse.py
matroid/src/streams.py
matroid/src/temporal_task.py
matroid/src/video_summary.py
matroid/src/videos.py
matroid-1.4.5.dist-info/licenses/LICENSE.txt
test/__init__.py
test/conftest.py
test/data.py
test/helper.py
test/test_accounts.py
test/test_collections.py
test/test_detectors_labels.py
test/test_images.py
test/test_streams.py
test/test_temporal_task.py
test/test_video_summary.py
test/test_videos.py
matroid-1.4.5.dist-info/METADATA
matroid-1.4.5.dist-info/WHEEL
matroid-1.4.5.dist-info/top_level.txt
matroid-1.4.5.dist-info/RECORD
