Metadata-Version: 2.4
Name: matroid
Version: 1.4.5
Summary: Matroid API Python Library
Home-page: https://github.com/matroid/matroid-python
Author: Matroid
Author-email: support@matroid.com
License-File: LICENSE.txt
Requires-Dist: requests
Dynamic: author
Dynamic: author-email
Dynamic: home-page
Dynamic: license-file
Dynamic: requires-dist
Dynamic: summary
